odoo/addons/mail_activity_tree_create/README.rst
odoo/addons/mail_activity_tree_create/__init__.py
odoo/addons/mail_activity_tree_create/__manifest__.py
odoo/addons/mail_activity_tree_create/readme/CONTRIBUTORS.md
odoo/addons/mail_activity_tree_create/readme/DESCRIPTION.md
odoo/addons/mail_activity_tree_create/readme/ROADMAP.md
odoo/addons/mail_activity_tree_create/readme/USAGE.md
odoo/addons/mail_activity_tree_create/static/description/icon.png
odoo/addons/mail_activity_tree_create/static/description/index.html
odoo/addons/mail_activity_tree_create/views/mail_activity_views.xml
odoo_addon_mail_activity_tree_create-17.0.1.0.0.1.dist-info/METADATA
odoo_addon_mail_activity_tree_create-17.0.1.0.0.1.dist-info/WHEEL
odoo_addon_mail_activity_tree_create-17.0.1.0.0.1.dist-info/top_level.txt
odoo_addon_mail_activity_tree_create-17.0.1.0.0.1.dist-info/RECORD
